{"Id":"5aba3cf9-60bf-4c24-8083-8924f75101d5","Topic":"Ch 01. Arrays and Strings","Question":"","Solution":"package Q1_08_Zero_Matrix;\r\n\r\nimport CtCILibrary.AssortedMethods;\r\n\r\npublic class QuestionA {\r\n\tpublic static void nullifyRow(int[][] matrix, int row) {\r\n\t\tfor (int j = 0; j < matrix[0].length; j++) {\r\n\t\t\tmatrix[row][j] = 0;\r\n\t\t}\t\t\r\n\t}\r\n\r\n\tpublic static void nullifyColumn(int[][] matrix, int col) {\r\n\t\tfor (int i = 0; i < matrix.length; i++) {\r\n\t\t\tmatrix[i][col] = 0;\r\n\t\t}\t\t\r\n\t}\t\t\t\r\n\t\r\n\tpublic static void setZeros(int[][] matrix) {\r\n\t\tboolean[] row = new boolean[matrix.length];\t\r\n\t\tboolean[] column = new boolean[matrix[0].length];\r\n\r\n\t\t// Store the row and column index with value 0\r\n\t\tfor (int i = 0; i < matrix.length; i++) {\r\n\t\t\tfor (int j = 0; j < matrix[0].length;j++) {\r\n\t\t\t\tif (matrix[i][j] == 0) {\r\n\t\t\t\t\trow[i] = true; \r\n\t\t\t\t\tcolumn[j] = true;\r\n\t\t \t\t}\r\n\t\t\t}\r\n\t\t}\r\n\t\t\r\n\t\t// Nullify rows\r\n\t\tfor (int i = 0; i < row.length; i++) {\r\n\t\t\tif (row[i]) {\r\n\t\t\t\tnullifyRow(matrix, i);\r\n\t\t\t}\r\n\t\t}\r\n\t\t\r\n\t\t// Nullify columns\r\n\t\tfor (int j = 0; j < column.length; j++) {\r\n\t\t\tif (column[j]) {\r\n\t\t\t\tnullifyColumn(matrix, j);\r\n\t\t\t}\r\n\t\t}\r\n\t}\t\r\n\t\r\n\tpublic static boolean matricesAreEqual(int[][] m1, int[][] m2) {\r\n\t\tif (m1.length != m2.length || m1[0].length != m2[0].length) {\r\n\t\t\treturn false;\r\n\t\t}\r\n\t\t\r\n\t\tfor (int k = 0; k < m1.length; k++) {\r\n\t\t\tfor (int j = 0; j < m1[0].length; j++) {\r\n\t\t\t\tif (m1[k][j] != m2[k][j]) {\r\n\t\t\t\t\treturn false;\r\n\t\t\t\t}\r\n\t\t\t}\r\n\t\t}\t\r\n\t\treturn true;\r\n\t}\r\n\t\r\n\tpublic static int[][] cloneMatrix(int[][] matrix) {\r\n\t\tint[][] c = new int[matrix.length][matrix[0].length];\r\n\t\tfor (int i = 0; i < matrix.length; i++) {\r\n\t\t\tfor (int j = 0; j < matrix[0].length; j++) {\r\n\t\t\t\tc[i][j] = matrix[i][j];\r\n\t\t\t}\r\n\t\t}\r\n\t\treturn c;\r\n\t}\r\n\t\r\n\tpublic static void main(String[] args) {\r\n\t\tint nrows = 10;\r\n\t\tint ncols = 15;\r\n\t\tint[][] matrix = AssortedMethods.randomMatrix(nrows, ncols, -10, 10);\t\t\r\n\r\n\t\tAssortedMethods.printMatrix(matrix);\r\n\t\t\r\n\t\tsetZeros(matrix);\r\n\t\t\r\n\t\tSystem.out.println();\r\n\t\t\r\n\t\tAssortedMethods.printMatrix(matrix);\r\n\t}\r\n}\r\n","Chapter":"Ch 01. Arrays and Strings"}