{"Id":"a4189c3e-f7db-4c5f-ab28-4325fcea3730","Topic":"Ch 16. Moderate","Question":"","Solution":"package Q16_23_Rand7_From_Rand5;\r\n\r\npublic class Question {\r\n\tpublic static int rand7() {\r\n\t\twhile (true) {\r\n\t\t\tint num = 5 * rand5() + rand5();\r\n\t\t\tif (num < 21) {\r\n\t\t\t\treturn num % 7;\r\n\t\t\t}\r\n\t\t}\r\n\t}\r\n\r\n\tpublic static int rand5() {\r\n\t\treturn (int) (Math.random() * 100) % 5;\r\n\t}\r\n\r\n\tpublic static void main(String[] args) {\r\n\t\t/* Test: call rand7 many times and inspect the results. */\r\n\t\tint[] arr = new int[7];\r\n\t\tint test_size = 1000000;\r\n\t\tfor(int k = 0; k < test_size; k++){\r\n\t\t\tarr[rand7()]++;\r\n\t\t}\r\n\r\n\t\tfor (int i = 0; i < 7; i++) {\r\n\t\t\tdouble percent = 100.0 * arr[i] / test_size;\r\n\t\t\tSystem.out.println(i + \" appeared \" + percent + \"% of the time.\");\r\n\t\t}\r\n\t}\r\n}\r\n","Chapter":"Ch 16. Moderate"}